{"stats":{"minecraft:mined":{"minecraft:dead_bush":6,"minecraft:yellow_stained_glass":1},"minecraft:used":{"minecraft:knowledge_book":5,"minecraft:wooden_hoe":6,"minecraft:glass_bottle":11,"minecraft:redstone":22,"minecraft:snowball":323},"minecraft:custom":{"minecraft:open_barrel":10,"minecraft:time_since_rest":80781,"minecraft:crouch_one_cm":6099,"minecraft:play_one_minute":80781,"minecraft:sprint_one_cm":328265,"minecraft:open_shulker_box":5,"minecraft:walk_one_cm":109119,"minecraft:sneak_time":1813,"minecraft:trigger_trapped_chest":35,"minecraft:jump":966,"minecraft:interact_with_blast_furnace":1,"minecraft:leave_game":1,"minecraft:time_since_death":80781,"minecraft:damage_resisted":84,"minecraft:fly_one_cm":281130,"minecraft:fall_one_cm":14366,"minecraft:tune_noteblock":31,"minecraft:use_cauldron":9,"minecraft:target_hit":32}},"DataVersion":2584}