{"stats":{"minecraft:crafted":{"minecraft:iron_ingot":23,"minecraft:air":0},"minecraft:picked_up":{"minecraft:ladder":9,"minecraft:iron_door":1,"minecraft:yellow_wool":1,"minecraft:torch":19,"minecraft:filled_map":47,"minecraft:structure_void":1,"minecraft:firework_rocket":1,"minecraft:compass":10,"minecraft:red_carpet":16,"minecraft:yellow_carpet":21,"minecraft:light_blue_stained_glass_pane":1,"minecraft:yellow_stained_glass_pane":1,"minecraft:book":34},"minecraft:mined":{"minecraft:red_carpet":13,"minecraft:yellow_wool":1,"minecraft:torch":19,"minecraft:yellow_carpet":21,"minecraft:dead_bush":59},"minecraft:custom":{"minecraft:time_since_rest":375680,"minecraft:sprint_one_cm":3370619,"minecraft:damage_taken":118,"minecraft:walk_one_cm":1284808,"minecraft:trigger_trapped_chest":307,"minecraft:drop":77,"minecraft:damage_dealt":40,"minecraft:target_hit":199,"minecraft:tune_noteblock":478,"minecraft:fly_one_cm":5731893,"minecraft:open_barrel":55,"minecraft:crouch_one_cm":79522,"minecraft:play_one_minute":1116180,"minecraft:open_shulker_box":178,"minecraft:deaths":1,"minecraft:sneak_time":32496,"minecraft:jump":23807,"minecraft:interact_with_blast_furnace":32,"minecraft:leave_game":17,"minecraft:time_since_death":375679,"minecraft:walk_on_water_one_cm":194,"minecraft:climb_one_cm":3168,"minecraft:damage_resisted":11091,"minecraft:use_cauldron":104,"minecraft:fall_one_cm":279195},"minecraft:dropped":{"minecraft:yellow_stained_glass_pane":1,"minecraft:filled_map":40,"minecraft:blue_stained_glass_pane":20,"minecraft:compass":11,"minecraft:black_stained_glass_pane":1,"minecraft:iron_door":1,"minecraft:book":17,"minecraft:orange_stained_glass_pane":9,"minecraft:firework_rocket":1},"minecraft:used":{"minecraft:wooden_hoe":59,"minecraft:glass_bottle":82,"minecraft:redstone":201,"minecraft:yellow_wool":1,"minecraft:torch":19,"minecraft:red_carpet":15,"minecraft:yellow_carpet":16,"minecraft:snowball":2130,"minecraft:knowledge_book":35}},"DataVersion":2584}